pfsc_examp/__init__.py
pfsc_examp/canon_arithmeticus.py
pfsc_examp/config.py
pfsc_examp/contexts.py
pfsc_examp/display.py
pfsc_examp/excep.py
pfsc_examp/util.py
pfsc_examp/calculate/__init__.py
pfsc_examp/calculate/server_calc.py
pfsc_examp/parameters/__init__.py
pfsc_examp/parameters/base.py
pfsc_examp/parameters/types/__init__.py
pfsc_examp/parameters/types/divisor.py
pfsc_examp/parameters/types/integer.py
pfsc_examp/parameters/types/numberfield.py
pfsc_examp/parameters/types/prime.py
pfsc_examp/parameters/types/primeideal.py
pfsc_examp/parameters/types/primres.py
pfsc_examp/parse/__init__.py
pfsc_examp/parse/algebraic.py
pfsc_examp/parse/display.py
pfsc_examp/parse/excep.py
pfsc_examp/parse/polynom.py
pfsc_examp/parse/sympy_allowed.py
pfsc_examp/parse/util.py
pfsc_examp-0.24.1.dist-info/LICENSE
pfsc_examp-0.24.1.dist-info/METADATA
pfsc_examp-0.24.1.dist-info/NOTICE
pfsc_examp-0.24.1.dist-info/WHEEL
pfsc_examp-0.24.1.dist-info/top_level.txt
pfsc_examp-0.24.1.dist-info/RECORD
